.VERSION
AUTHORS.rst
CONTRIBUTING.rst
HISTORY.rst
LICENSE
MANIFEST.in
Pipfile
Pipfile.lock
README.rst
USAGE.rst
dev-requirements.txt
requirements.txt
setup.cfg
setup.py
chefsessionlib/.VERSION
chefsessionlib/AUTHORS.rst
chefsessionlib/CONTRIBUTING.rst
chefsessionlib/HISTORY.rst
chefsessionlib/LICENSE
chefsessionlib/Pipfile
chefsessionlib/Pipfile.lock
chefsessionlib/README.rst
chefsessionlib/USAGE.rst
chefsessionlib/__init__.py
chefsessionlib/_version.py
chefsessionlib/chefsessionlib.py
chefsessionlib/chefsessionlibexceptions.py
chefsessionlib/dev-requirements.txt
chefsessionlib/requirements.txt
chefsessionlib.egg-info/PKG-INFO
chefsessionlib.egg-info/SOURCES.txt
chefsessionlib.egg-info/dependency_links.txt
chefsessionlib.egg-info/not-zip-safe
chefsessionlib.egg-info/requires.txt
chefsessionlib.egg-info/top_level.txt
docs/Makefile
docs/authors.rst
docs/conf.py
docs/contributing.rst
docs/history.rst
docs/index.rst
docs/installation.rst
docs/readme.rst
docs/usage.rst
tests/test_chefsessionlib.py
tests/fixtures/__init__.py
tests/fixtures/configuration.py