Metadata-Version: 2.1
Name: chefsessionlib
Version: 0.1.1
Summary: A requests Session compatible library that implements Chef server authentication transparently on the requests.
Home-page: https://github.com/schubergphilis/chefsessionlib.git
Author: Costas Tyfoxylos, Daan de Goede
Author-email: ctyfoxylos@schubergphilis.com,  ddegoede@schubergphilis.com
License: Apache Software License 2.0
Keywords: chefsessionlib,chef authentication,requests session
Classifier: Development Status :: 4 - Beta
Classifier: Intended Audience :: Developers
Classifier: License :: OSI Approved :: Apache Software License
Classifier: Natural Language :: English
Classifier: Programming Language :: Python :: 3.9
License-File: LICENSE
License-File: AUTHORS.rst
Requires-Dist: requests>=2.31.0; python_version >= "3.7"
Requires-Dist: rsa>=4.9; python_version >= "3.6" and python_version < "4"
